beampy/__init__.py
beampy/cache.py
beampy/commands.py
beampy/document.py
beampy/exports.py
beampy/functions.py
beampy/geometry.py
beampy/slide_render_functions.py
beampy/utils.py
beampy/modules/__init__.py
beampy/modules/animatesvg.py
beampy/modules/arrow.py
beampy/modules/biblio.py
beampy/modules/box.py
beampy/modules/code.py
beampy/modules/core.py
beampy/modules/figure.py
beampy/modules/iframe.py
beampy/modules/itemize.py
beampy/modules/maketitle.py
beampy/modules/svg.py
beampy/modules/table.py
beampy/modules/text.py
beampy/modules/text.py.back
beampy/modules/tikz.py
beampy/modules/title.py
beampy/modules/toc.py
beampy/modules/video.py
beampy/scour/__init__.py
beampy/scour/scour.py
beampy/scour/svg_regex.py
beampy/scour/svg_transform.py
beampy/scour/yocto_css.py
beampy/statics/__init__.py
beampy/statics/default_theme.py
beampy/statics/footer_V2.html
beampy/statics/header_V2.html
beampy/statics/jquery.js
beampy/statics/bokeh/bokeh.min.css
beampy/statics/bokeh/bokeh.min.js
beampy/themes/BeamerFrankfurt_theme.py
beampy/themes/ComplicatedBlue_theme.py
beampy/themes/HipsterChic_theme.py
beampy/themes/SimpleBlue_theme.py
beampy/themes/__init__.py
beampy_slideshow-0.5.5.post3.dist-info/LICENSE
beampy_slideshow-0.5.5.post3.dist-info/METADATA
beampy_slideshow-0.5.5.post3.dist-info/WHEEL
beampy_slideshow-0.5.5.post3.dist-info/top_level.txt
beampy_slideshow-0.5.5.post3.dist-info/RECORD
