Metadata-Version: 2.1
Name: beampy-slideshow
Version: 0.5.5.post3
Summary: A python tool to create simple HTML5 presentation slideshow
Home-page: https://github.com/hchauvet/beampy
Author: Hugo Chauvet
Author-email: hugo.chauvet@protonmail.com
License: UNKNOWN
Platform: UNKNOWN
Classifier: Programming Language :: Python :: 2 
Classifier: Programming Language :: Python :: 3 
Classifier: Topic :: Multimedia :: Graphics :: Presentation
Classifier: Topic :: Multimedia :: Graphics :: Editors :: Vector-Based 
Classifier: Topic :: Text Processing :: Markup :: LaTeX
Classifier: Topic :: Text Processing :: Markup :: HTML
Classifier: Topic :: Text Processing
Classifier: License :: OSI Approved :: GNU General Public License v3 (GPLv3)
Requires-Dist: beautifulsoup4
Requires-Dist: pillow
Requires-Dist: six
Requires-Dist: lxml
Requires-Dist: bibtexparser
